{
  "id": "multilocator-test_room",
  "locators": [
    {
      "id": "ble-pd-588E8166AF43",
      "coordinate": {
        "x": 2.4,
        "y": 0.0,
        "z": 0.0
      },
      "orientation": {
        "x": 0.0,
        "y": 0.0,
        "z": 0.0
      }
    },
    {
      "id": "ble-pd-84FD27EEE4FF",
      "coordinate": {
        "x": 0.0,
        "y": 4.8,
        "z": 0.0
      },
      "orientation": {
        "x": 0.0,
        "y": 0.0,
        "z": 0.0
      }
    },
    {
      "id": "ble-pd-84FD27EEE4D6",
      "coordinate": {
        "x": 2.4,
        "y": 4.8,
        "z": 0.0
      },
      "orientation": {
        "x": 0.0,
        "y": 0.0,
        "z": 0.0
      }
    }
  ]
}